pdf2m4b/__init__.py
pdf2m4b/logger_config.py
pdf2m4b/main.py
pdf2m4b/make_m4b.py
pdf2m4b/md_to_folders.py
pdf2m4b/pdf_to_md.py
pdf2m4b/tts_polly.py
pdf2m4b-0.1.2.dist-info/METADATA
pdf2m4b-0.1.2.dist-info/WHEEL
pdf2m4b-0.1.2.dist-info/RECORD
