Metadata-Version: 2.3
Name: pdf2m4b
Version: 0.1.2
Summary: A tool for converting PDFs to M4B audiobooks using AWS polly.
Home-page: https://github.com/aleloi/pdf2m4b
License: MIT
Author: Alex Loiko
Author-email: alexandreloiko@gmail.com
Requires-Python: >=3.9
Classifier: License :: OSI Approved :: MIT License
Classifier: Programming Language :: Python :: 3
Classifier: Programming Language :: Python :: 3.9
Classifier: Programming Language :: Python :: 3.10
Classifier: Programming Language :: Python :: 3.11
Classifier: Programming Language :: Python :: 3.12
Classifier: Programming Language :: Python :: 3.13
Requires-Dist: boto3 (>=1.36.11,<2.0.0)
Requires-Dist: pymupdf4llm (>=0.0.17,<0.0.18)
Requires-Dist: rich (>=13.9.4,<14.0.0)
Requires-Dist: structlog (>=25.1.0,<26.0.0)
